CONTRIBUTING.md
LICENSE
MANIFEST.in
README.md
settings.ini
setup.py
quixotic/__init__.py
quixotic/_nbdev.py
quixotic/core.py
quixotic/utils.py
quixotic.egg-info/PKG-INFO
quixotic.egg-info/SOURCES.txt
quixotic.egg-info/dependency_links.txt
quixotic.egg-info/entry_points.txt
quixotic.egg-info/not-zip-safe
quixotic.egg-info/requires.txt
quixotic.egg-info/top_level.txt
quixotic/optimization/__init__.py
quixotic/optimization/base.py
quixotic/optimization/qaoa.py
quixotic/optimization/quantum_annealing.py