Metadata-Version: 2.1
Name: quixotic
Version: 0.0.5
Summary: Quixotic
Home-page: https://github.com/amaiya/quixotic/tree/main/
Author: Arun S. Maiya
Author-email: arun@maiya.net
License: Apache Software License 2.0
Keywords: quantum-computing optimization graph-optimization
Platform: UNKNOWN
Classifier: Development Status :: 3 - Alpha
Classifier: Intended Audience :: Developers
Classifier: Natural Language :: English
Classifier: Programming Language :: Python :: 3.7
Classifier: Programming Language :: Python :: 3.8
Classifier: License :: OSI Approved :: Apache Software License
Requires-Python: >=3.7
Provides-Extra: dev
